{\rtf1\ansi\ansicpg1252\cocoartf2868
\cocoatextscaling0\cocoaplatform0{\fonttbl\f0\fswiss\fcharset0 Helvetica;}
{\colortbl;\red255\green255\blue255;}
{\*\expandedcolortbl;;}
\margl1440\margr1440\vieww11520\viewh8400\viewkind0
\pard\tx720\tx1440\tx2160\tx2880\tx3600\tx4320\tx5040\tx5760\tx6480\tx7200\tx7920\tx8640\pardirnatural\partightenfactor0

\f0\fs24 \cf0 \{\
    "IMG_6048.jpeg": \{\
        "archivo": "IMG_6048.jpeg",\
        "titulo": "Cuernitos",\
        "categoria": "Cakes and cookies",\
        "palabras_clave": [\
            "nuez"\
        ]\
    \},\
    "IMG_6050.jpeg": \{\
        "archivo": "IMG_6050.jpeg",\
        "titulo": "Galletas de nuez",\
        "categoria": "Cakes and cookies",\
        "palabras_clave": [\
            "nuez"\
        ]\
    \},\
    "IMG_6052.jpeg": \{\
        "archivo": "IMG_6052.jpeg",\
        "titulo": "Cheese Bisquits",\
        "categoria": "Cakes and cookies",\
        "palabras_clave": [\
            "queso",\
            "nuez"\
        ]\
    \},\
    "IMG_6054.jpeg": \{\
        "archivo": "IMG_6054.jpeg",\
        "titulo": "Chocolate Drops",\
        "categoria": "Cakes and cookies",\
        "palabras_clave": [\
            "chocolate"\
        ]\
    \},\
    "IMG_6055.jpeg": \{\
        "archivo": "IMG_6055.jpeg",\
        "titulo": "Chocolate Drops 2",\
        "categoria": "Cakes and cookies",\
        "palabras_clave": [\
            "chocolate"\
        ]\
    \},\
    "IMG_6056.jpeg": \{\
        "archivo": "IMG_6056.jpeg",\
        "titulo": "Pastel imposible",\
        "categoria": "Cakes and cookies",\
        "palabras_clave": [\
            "coco",\
            "nuez"\
        ]\
    \},\
    "IMG_6057.jpeg": \{\
        "archivo": "IMG_6057.jpeg",\
        "titulo": "Pastel imposible 2",\
        "categoria": "Cakes and cookies",\
        "palabras_clave": [\
            "coco nuez"\
        ]\
    \},\
    "IMG_6058.jpeg": \{\
        "archivo": "IMG_6058.jpeg",\
        "titulo": "Masa para Empanadas",\
        "categoria": "Cakes and cookies",\
        "palabras_clave": []\
    \},\
    "IMG_6060.jpeg": \{\
        "archivo": "IMG_6060.jpeg",\
        "titulo": "Brownies",\
        "categoria": "Cakes and cookies",\
        "palabras_clave": [\
            "chocolate"\
        ]\
    \},\
    "IMG_6061.jpeg": \{\
        "archivo": "IMG_6061.jpeg",\
        "titulo": "Fudge cake",\
        "categoria": "Cakes and cookies",\
        "palabras_clave": [\
            "chocolate"\
        ]\
    \},\
    "IMG_6062.jpeg": \{\
        "archivo": "IMG_6062.jpeg",\
        "titulo": "Orange Cookies",\
        "categoria": "Cakes and cookies",\
        "palabras_clave": [\
            "naranja"\
        ]\
    \},\
    "IMG_6063.jpeg": \{\
        "archivo": "IMG_6063.jpeg",\
        "titulo": "Orange cookies 2",\
        "categoria": "Cakes and cookies",\
        "palabras_clave": [\
            "naranja"\
        ]\
    \},\
    "IMG_6064.jpeg": \{\
        "archivo": "IMG_6064.jpeg",\
        "titulo": "Bolitas de co\'f1ac",\
        "categoria": "Cakes and cookies",\
        "palabras_clave": [\
            "nuez"\
        ]\
    \},\
    "IMG_6065.jpeg": \{\
        "archivo": "IMG_6065.jpeg",\
        "titulo": "IMG 6065",\
        "categoria": "Cakes and cookies",\
        "palabras_clave": []\
    \},\
    "IMG_6066.jpeg": \{\
        "archivo": "IMG_6066.jpeg",\
        "titulo": "Galletas coco",\
        "categoria": "Cakes and cookies",\
        "palabras_clave": [\
            "nuez",\
            "coco"\
        ]\
    \},\
    "IMG_6067.jpeg": \{\
        "archivo": "IMG_6067.jpeg",\
        "titulo": "Galletas coco 2",\
        "categoria": "Cakes and cookies",\
        "palabras_clave": [\
            "nuez",\
            "coco"\
        ]\
    \},\
    "IMG_6068.jpeg": \{\
        "archivo": "IMG_6068.jpeg",\
        "titulo": "Raisin Oatmeal classics",\
        "categoria": "Cakes and cookies",\
        "palabras_clave": [\
            "avena",\
            "pasas"\
        ]\
    \},\
    "IMG_6069.jpeg": \{\
        "archivo": "IMG_6069.jpeg",\
        "titulo": "Raisin Oatmeal classics 2",\
        "categoria": "Cakes and cookies",\
        "palabras_clave": [\
            "avena",\
            "pasas"\
        ]\
    \},\
    "IMG_6070.jpeg": \{\
        "archivo": "IMG_6070.jpeg",\
        "titulo": "Anonumo de manzana",\
        "categoria": "Cakes and cookies",\
        "palabras_clave": [\
            "manzana"\
        ]\
    \},\
    "IMG_6071.jpeg": \{\
        "archivo": "IMG_6071.jpeg",\
        "titulo": "Anonimo de manzana 2",\
        "categoria": "Cakes and cookies",\
        "palabras_clave": [\
            "manzana"\
        ]\
    \},\
    "IMG_6072.jpeg": \{\
        "archivo": "IMG_6072.jpeg",\
        "titulo": "Pan de manzana",\
        "categoria": "Cakes and cookies",\
        "palabras_clave": [\
            "manzana"\
        ]\
    \},\
    "IMG_6073.jpeg": \{\
        "archivo": "IMG_6073.jpeg",\
        "titulo": "Pan de manzana 2",\
        "categoria": "Cakes and cookies",\
        "palabras_clave": [\
            "manzana"\
        ]\
    \},\
    "IMG_6074.jpeg": \{\
        "archivo": "IMG_6074.jpeg",\
        "titulo": "Mixed Berry Coffee Cake",\
        "categoria": "Cakes and cookies",\
        "palabras_clave": [\
            "berries",\
            "almendras"\
        ]\
    \},\
    "IMG_6075.jpeg": \{\
        "archivo": "IMG_6075.jpeg",\
        "titulo": "Mixed Berry Coffee Cake 2",\
        "categoria": "Cakes and cookies",\
        "palabras_clave": [\
            "berries",\
            "almendras"\
        ]\
    \},\
    "IMG_6076.jpeg": \{\
        "archivo": "IMG_6076.jpeg",\
        "titulo": "Bet\'fan ake domino",\
        "categoria": "Cakes and cookies",\
        "palabras_clave": []\
    \},\
    "IMG_6077.jpeg": \{\
        "archivo": "IMG_6077.jpeg",\
        "titulo": "IMG 6077",\
        "categoria": "Cakes and cookies",\
        "palabras_clave": []\
    \},\
    "IMG_6078.jpeg": \{\
        "archivo": "IMG_6078.jpeg",\
        "titulo": "Cake de Zanahoria",\
        "categoria": "Cakes and cookies",\
        "palabras_clave": [\
            "zanahoria",\
            "nuez"\
        ]\
    \},\
    "IMG_6079.jpeg": \{\
        "archivo": "IMG_6079.jpeg",\
        "titulo": "Bet\'fan de queso con crema",\
        "categoria": "Cakes and cookies",\
        "palabras_clave": [\
            "queso filadelfia"\
        ]\
    \},\
    "IMG_6080.jpeg": \{\
        "archivo": "IMG_6080.jpeg",\
        "titulo": "Hersheys special cake 2",\
        "categoria": "Cakes and cookies",\
        "palabras_clave": []\
    \},\
    "IMG_6081.jpeg": \{\
        "archivo": "IMG_6081.jpeg",\
        "titulo": "Hersheys special cake",\
        "categoria": "Cakes and cookies",\
        "palabras_clave": [\
            "cocoa"\
        ]\
    \},\
    "IMG_6082.jpeg": \{\
        "archivo": "IMG_6082.jpeg",\
        "titulo": "Collectors cocoa cake",\
        "categoria": "Cakes and cookies",\
        "palabras_clave": []\
    \},\
    "IMG_6083.jpeg": \{\
        "archivo": "IMG_6083.jpeg",\
        "titulo": "Collectors cocoa cake 2",\
        "categoria": "Cakes and cookies",\
        "palabras_clave": []\
    \},\
    "IMG_6084.jpeg": \{\
        "archivo": "IMG_6084.jpeg",\
        "titulo": "Cake chocolate",\
        "categoria": "Cakes and cookies",\
        "palabras_clave": [\
            "chocolate"\
        ]\
    \},\
    "IMG_6085.jpeg": \{\
        "archivo": "IMG_6085.jpeg",\
        "titulo": "Cake chocolate",\
        "categoria": "Cakes and cookies",\
        "palabras_clave": []\
    \},\
    "IMG_6086.jpeg": \{\
        "archivo": "IMG_6086.jpeg",\
        "titulo": "Pastel de pi\'f1a invertido",\
        "categoria": "Cakes and cookies",\
        "palabras_clave": [\
            "pi\'f1a"\
        ]\
    \},\
    "IMG_6087.jpeg": \{\
        "archivo": "IMG_6087.jpeg",\
        "titulo": "Pastel de pi\'f1a invertido",\
        "categoria": "Cakes and cookies",\
        "palabras_clave": [\
            "pi\'f1a"\
        ]\
    \},\
    "IMG_6088.jpeg": \{\
        "archivo": "IMG_6088.jpeg",\
        "titulo": "Fruit Cake",\
        "categoria": "Cakes and cookies",\
        "palabras_clave": [\
            "frutas"\
        ]\
    \},\
    "IMG_6089.jpeg": \{\
        "archivo": "IMG_6089.jpeg",\
        "titulo": "Fruit Cake",\
        "categoria": "Cakes and cookies",\
        "palabras_clave": [\
            "frutas"\
        ]\
    \},\
    "IMG_6090.jpeg": \{\
        "archivo": "IMG_6090.jpeg",\
        "titulo": "Cake de chocolate",\
        "categoria": "Cakes and cookies",\
        "palabras_clave": [\
            "cocoa"\
        ]\
    \},\
    "IMG_6091.jpeg": \{\
        "archivo": "IMG_6091.jpeg",\
        "titulo": "Cake de chocolate",\
        "categoria": "Cakes and cookies",\
        "palabras_clave": [\
            "cocoa"\
        ]\
    \},\
    "IMG_6092.jpeg": \{\
        "archivo": "IMG_6092.jpeg",\
        "titulo": "Summer fruit kuchen",\
        "categoria": "Cakes and cookies",\
        "palabras_clave": [\
            "durazno",\
            "berries"\
        ]\
    \},\
    "IMG_6093.jpeg": \{\
        "archivo": "IMG_6093.jpeg",\
        "titulo": "Summer fruit kuchen",\
        "categoria": "Cakes and cookies",\
        "palabras_clave": [\
            "durazno",\
            "berries"\
        ]\
    \},\
    "IMG_6094.jpeg": \{\
        "archivo": "IMG_6094.jpeg",\
        "titulo": "Cinamon Crumb Cake",\
        "categoria": "Cakes and cookies",\
        "palabras_clave": [\
            "canela"\
        ]\
    \},\
    "IMG_6096.jpeg": \{\
        "archivo": "IMG_6096.jpeg",\
        "titulo": "Glaze (Glaceado)",\
        "categoria": "Cakes and cookies",\
        "palabras_clave": []\
    \},\
    "IMG_6097.jpeg": \{\
        "archivo": "IMG_6097.jpeg",\
        "titulo": "Glaceado (otro)",\
        "categoria": "Cakes and cookies",\
        "palabras_clave": []\
    \},\
    "IMG_6098.jpeg": \{\
        "archivo": "IMG_6098.jpeg",\
        "titulo": "Coffee cake",\
        "categoria": "Cakes and cookies",\
        "palabras_clave": []\
    \},\
    "IMG_6099.jpeg": \{\
        "archivo": "IMG_6099.jpeg",\
        "titulo": "Coffee cake 2",\
        "categoria": "Cakes and cookies",\
        "palabras_clave": []\
    \},\
    "IMG_6100.jpeg": \{\
        "archivo": "IMG_6100.jpeg",\
        "titulo": "Hojarascas",\
        "categoria": "Cakes and cookies",\
        "palabras_clave": []\
    \},\
    "IMG_6102.jpeg": \{\
        "archivo": "IMG_6102.jpeg",\
        "titulo": "Galletas de chocolate",\
        "categoria": "Cakes and cookies",\
        "palabras_clave": [\
            "chocolate",\
            "nuez"\
        ]\
    \},\
    "IMG_6103.jpeg": \{\
        "archivo": "IMG_6103.jpeg",\
        "titulo": "Galletas de chocolate 2",\
        "categoria": "Cakes and cookies",\
        "palabras_clave": [\
            "chocolate",\
            "nuez"\
        ]\
    \},\
    "IMG_6104.jpeg": \{\
        "archivo": "IMG_6104.jpeg",\
        "titulo": "Sopalpillas",\
        "categoria": "Cakes and cookies",\
        "palabras_clave": []\
    \},\
    "IMG_6105.jpeg": \{\
        "archivo": "IMG_6105.jpeg",\
        "titulo": "Sopalpillas 2",\
        "categoria": "Cakes and cookies",\
        "palabras_clave": []\
    \},\
    "IMG_6106.jpeg": \{\
        "archivo": "IMG_6106.jpeg",\
        "titulo": "Galletas de ajonjol\'ed",\
        "categoria": "Cakes and cookies",\
        "palabras_clave": [\
            "avena",\
            "pasas",\
            "ajonjol\'ed"\
        ]\
    \},\
    "IMG_6107.jpeg": \{\
        "archivo": "IMG_6107.jpeg",\
        "titulo": "Galletas de ajonjol\'ed 2",\
        "categoria": "Cakes and cookies",\
        "palabras_clave": [\
            "avena",\
            "pasas",\
            "ajonjol\'ed"\
        ]\
    \},\
    "IMG_6108.jpeg": \{\
        "archivo": "IMG_6108.jpeg",\
        "titulo": "Bu\'f1uelos",\
        "categoria": "Cakes and cookies",\
        "palabras_clave": []\
    \},\
    "IMG_6109.jpeg": \{\
        "archivo": "IMG_6109.jpeg",\
        "titulo": "Bu\'f1uelos 2",\
        "categoria": "Cakes and cookies",\
        "palabras_clave": []\
    \},\
    "IMG_6110.jpeg": \{\
        "archivo": "IMG_6110.jpeg",\
        "titulo": "Galletas de chocolate (otra)",\
        "categoria": "Cakes and cookies",\
        "palabras_clave": [\
            "chocolate"\
        ]\
    \},\
    "IMG_6111.jpeg": \{\
        "archivo": "IMG_6111.jpeg",\
        "titulo": "Galletas de chocolate (otra) 2",\
        "categoria": "Cakes and cookies",\
        "palabras_clave": [\
            "chocolate"\
        ]\
    \},\
    "IMG_6112.jpeg": \{\
        "archivo": "IMG_6112.jpeg",\
        "titulo": "Gumdrop cookies",\
        "categoria": "Cakes and cookies",\
        "palabras_clave": [\
            "avena",\
            "coco",\
            "gomitas"\
        ]\
    \},\
    "IMG_6113.jpeg": \{\
        "archivo": "IMG_6113.jpeg",\
        "titulo": "Gumdrop cookies 2",\
        "categoria": "Cakes and cookies",\
        "palabras_clave": [\
            "avena",\
            "coco",\
            "gomitas"\
        ]\
    \},\
    "IMG_6114.jpeg": \{\
        "archivo": "IMG_6114.jpeg",\
        "titulo": "Cake de Zanahoria (otro=",\
        "categoria": "Cakes and cookies",\
        "palabras_clave": [\
            "zanahoria",\
            "nuez"\
        ]\
    \},\
    "IMG_6115.jpeg": \{\
        "archivo": "IMG_6115.jpeg",\
        "titulo": "Bet\'fan de queso con crema",\
        "categoria": "Otros",\
        "palabras_clave": [\
            "queso filadelfia"\
        ]\
    \},\
\
\
\
\
    "IMG_6147.jpeg": \{\
        "archivo": "IMG_6147.jpeg",\
        "titulo": "Kaffe Kutchen",\
        "categoria": "quick breads",\
        "palabras_clave": []\
    \},\
    "IMG_6148.jpeg": \{\
        "archivo": "IMG_6148.jpeg",\
        "titulo": "Kaffe kutchen 2",\
        "categoria": "quick breads",\
        "palabras_clave": []\
    \},\
    "IMG_6149.jpeg": \{\
        "archivo": "IMG_6149.jpeg",\
        "titulo": "Queso de linazaIMG 6149",\
        "categoria": "quick breads",\
        "palabras_clave": [\
            "Linaza",\
            "Aceite ede coco"\
        ]\
    \},\
    "IMG_6150.jpeg": \{\
        "archivo": "IMG_6150.jpeg",\
        "titulo": "Blueberry Muffins",\
        "categoria": "quick breads",\
        "palabras_clave": [\
            "blueberries"\
        ]\
    \},\
    "IMG_6151.jpeg": \{\
        "archivo": "IMG_6151.jpeg",\
        "titulo": "Blueberry muffins (2)",\
        "categoria": "quick breads",\
        "palabras_clave": [\
            "Blueberry aceite de coco"\
        ]\
    \},\
    "IMG_6152.jpeg": \{\
        "archivo": "IMG_6152.jpeg",\
        "titulo": "Hotacka de avena",\
        "categoria": "quick breads",\
        "palabras_clave": [\
            "Acena",\
            "aceite de coco"\
        ]\
    \},\
    "IMG_6153.jpeg": \{\
        "archivo": "IMG_6153.jpeg",\
        "titulo": "Hotcake de avena",\
        "categoria": "quick breads",\
        "palabras_clave": [\
            "Avena",\
            "aceito de coco"\
        ]\
    \},\
    "IMG_6154.jpeg": \{\
        "archivo": "IMG_6154.jpeg",\
        "titulo": "Baking Poweder Biscuits",\
        "categoria": "quick breads",\
        "palabras_clave": []\
    \},\
    "IMG_6155.jpeg": \{\
        "archivo": "IMG_6155.jpeg",\
        "titulo": "IBaking powder bisquits",\
        "categoria": "quick breads",\
        "palabras_clave": []\
    \},\
    "IMG_6156.jpeg": \{\
        "archivo": "IMG_6156.jpeg",\
        "titulo": "Rosca de naranja",\
        "categoria": "quick breads",\
        "palabras_clave": [\
            "Naranja"\
        ]\
    \},\
    "IMG_6157.jpeg": \{\
        "archivo": "IMG_6157.jpeg",\
        "titulo": "Rosca de naranja (2)",\
        "categoria": "quick breads",\
        "palabras_clave": [\
            "Naranja"\
        ]\
    \},\
    "IMG_6158.jpeg": \{\
        "archivo": "IMG_6158.jpeg",\
        "titulo": "Pan de pl\'e1tano",\
        "categoria": "quick breads",\
        "palabras_clave": [\
            "Pl\'e1tano",\
            "nuez"\
        ]\
    \},\
    "IMG_6159.jpeg": \{\
        "archivo": "IMG_6159.jpeg",\
        "titulo": "Pan de pl\'e1tano (2)",\
        "categoria": "quick breads",\
        "palabras_clave": [\
            "Pl\'e1tanos"\
        ]\
    \},\
    "IMG_6160.jpeg": \{\
        "archivo": "IMG_6160.jpeg",\
        "titulo": "German Sweet Chocolate crean cheese brownies",\
        "categoria": "quick breads",\
        "palabras_clave": [\
            "Chocolate dulce",\
            "queso philadelphia"\
        ]\
    \},\
    "IMG_6161.jpeg": \{\
        "archivo": "IMG_6161.jpeg",\
        "titulo": "German sweet chocolat pie",\
        "categoria": "quick breads",\
        "palabras_clave": [\
            "Chocolate dulce"\
        ]\
    \},\
    "IMG_6162.jpeg": \{\
        "archivo": "IMG_6162.jpeg",\
        "titulo": "Muffins de caf\'e9",\
        "categoria": "quick breads",\
        "palabras_clave": [\
            "Capuchio"\
        ]\
    \},\
    "IMG_6163.jpeg": \{\
        "archivo": "IMG_6163.jpeg",\
        "titulo": "Muffins de cafe (2)",\
        "categoria": "quick breads",\
        "palabras_clave": [\
            "Capuchino"\
        ]\
    \},\
    "IMG_6164.jpeg": \{\
        "archivo": "IMG_6164.jpeg",\
        "titulo": "Raisin Oatmeal",\
        "categoria": "quick breads",\
        "palabras_clave": [\
            "Avena",\
            "pasas"\
        ]\
    \},\
    "IMG_6165.jpeg": \{\
        "archivo": "IMG_6165.jpeg",\
        "titulo": "Brownies",\
        "categoria": "quick breads",\
        "palabras_clave": [\
            "Chocolate amargo",\
            "nuez picada"\
        ]\
    \},\
    "IMG_6166.jpeg": \{\
        "archivo": "IMG_6166.jpeg",\
        "titulo": "Briwnies (2)",\
        "categoria": "quick breads",\
        "palabras_clave": [\
            "Chocolate amargo",\
            "nuez picada"\
        ]\
    \},\
    "IMG_6167.jpeg": \{\
        "archivo": "IMG_6167.jpeg",\
        "titulo": "Panecillos de maiz",\
        "categoria": "quick breads",\
        "palabras_clave": [\
            "Harina maiz",\
            "nuez picada"\
        ]\
    \},\
    "IMG_6168.jpeg": \{\
        "archivo": "IMG_6168.jpeg",\
        "titulo": "Panecillos de maiz (2=",\
        "categoria": "quick breads",\
        "palabras_clave": [\
            "Harina maiz",\
            "nuez picada"\
        ]\
    \},\
    "IMG_6169.jpeg": \{\
        "archivo": "IMG_6169.jpeg",\
        "titulo": "Panquecitoa allbran",\
        "categoria": "quick breads",\
        "palabras_clave": [\
            "Allbran"\
        ]\
    \},\
    "IMG_6170.jpeg": \{\
        "archivo": "IMG_6170.jpeg",\
        "titulo": "panquecitos de allbran",\
        "categoria": "quick breads",\
        "palabras_clave": [\
            "Allbran"\
        ]\
    \},\
    "IMG_6171.jpeg": \{\
        "archivo": "IMG_6171.jpeg",\
        "titulo": "Panecillos de maiz",\
        "categoria": "quick breads",\
        "palabras_clave": [\
            "bueces picadas",\
            "harina de maiz"\
        ]\
    \},\
    "IMG_6172.jpeg": \{\
        "archivo": "IMG_6172.jpeg",\
        "titulo": "Panecillos de maiz",\
        "categoria": "quick breads",\
        "palabras_clave": [\
            "Harina de maiz",\
            "nuez picada"\
        ]\
    \},\
    "IMG_6173.jpeg": \{\
        "archivo": "IMG_6173.jpeg",\
        "titulo": "Oh Boy Waffles",\
        "categoria": "quick breads",\
        "palabras_clave": []\
    \},\
    "IMG_6174.jpeg": \{\
        "archivo": "IMG_6174.jpeg",\
        "titulo": "Oh boy waffles (2)",\
        "categoria": "quick breads",\
        "palabras_clave": []\
    \},\
    "IMG_6175.jpeg": \{\
        "archivo": "IMG_6175.jpeg",\
        "titulo": "Oh boy waffles (3)",\
        "categoria": "quick breads",\
        "palabras_clave": []\
    \},\
    "IMG_6176.jpeg": \{\
        "archivo": "IMG_6176.jpeg",\
        "titulo": "Oh boy wafles (4)",\
        "categoria": "quick breads",\
        "palabras_clave": []\
    \},\
    "IMG_6177.jpeg": \{\
        "archivo": "IMG_6177.jpeg",\
        "titulo": "Quecos de pl\'e1tano",\
        "categoria": "quick breads",\
        "palabras_clave": [\
            "Plat\'e1nos",\
            "nuez picada"\
        ]\
    \},\
    "IMG_6178.jpeg": \{\
        "archivo": "IMG_6178.jpeg",\
        "titulo": "IMG 6178",\
        "categoria": "",\
        "palabras_clave": []\
    \},\
    "IMG_6179.jpeg": \{\
        "archivo": "IMG_6179.jpeg",\
        "titulo": "IMQuecos de pl\'e1tano (2)G 6179",\
        "categoria": "quick breads",\
        "palabras_clave": [\
            "Pl\'e1tanos"\
        ]\
    \},\
    "IMG_6180.jpeg": \{\
        "archivo": "IMG_6180.jpeg",\
        "titulo": "Galletas de mantequilla",\
        "categoria": "quick breads",\
        "palabras_clave": []\
    \},\
    "IMG_6181.jpeg": \{\
        "archivo": "IMG_6181.jpeg",\
        "titulo": "Blueberries cofeecake",\
        "categoria": "quick breads",\
        "palabras_clave": [\
            "blueberries"\
        ]\
    \},\
    "IMG_6182.jpeg": \{\
        "archivo": "IMG_6182.jpeg",\
        "titulo": "Blueberries coffeecake",\
        "categoria": "quick breads",\
        "palabras_clave": [\
            "Blueberries"\
        ]\
    \},\
    "IMG_6183.jpeg": \{\
        "archivo": "IMG_6183.jpeg",\
        "titulo": "IMCupcakes",\
        "categoria": "quick breads",\
        "palabras_clave": [\
            "Cocoa"\
        ]\
    \},\
    "IMG_6184.jpeg": \{\
        "archivo": "IMG_6184.jpeg",\
        "titulo": "cake y bet\'fan chocolate",\
        "categoria": "quick breads",\
        "palabras_clave": [\
            "Devils food",\
            "chocolate"\
        ]\
    \},\
    "IMG_6185.jpeg": \{\
        "archivo": "IMG_6185.jpeg",\
        "titulo": "Chocolate Butter Frosting",\
        "categoria": "quick breads",\
        "palabras_clave": []\
    \},\
    "IMG_6186.jpeg": \{\
        "archivo": "IMG_6186.jpeg",\
        "titulo": "Butter cream frosting",\
        "categoria": "quick breads",\
        "palabras_clave": []\
    \},\
    "IMG_6187.jpeg": \{\
        "archivo": "IMG_6187.jpeg",\
        "titulo": "IButter crea Frosting (2)",\
        "categoria": "quick breads",\
        "palabras_clave": []\
    \},\
    "IMG_6188.jpeg": \{\
        "archivo": "IMG_6188.jpeg",\
        "titulo": "Bet\'fan de 7 minutos",\
        "categoria": "quick breads",\
        "palabras_clave": [\
            "Miel karo"\
        ]\
    \},\
    "IMG_6189.jpeg": \{\
        "archivo": "IMG_6189.jpeg",\
        "titulo": "Sea foam fluffy frostings",\
        "categoria": "quick breads",\
        "palabras_clave": []\
    \},\
    "IMG_6190.jpeg": \{\
        "archivo": "IMG_6190.jpeg",\
        "titulo": "Whoppies",\
        "categoria": "quick breads",\
        "palabras_clave": []\
    \},\
    "IMG_6191.jpeg": \{\
        "archivo": "IMG_6191.jpeg",\
        "titulo": "whopies (2)",\
        "categoria": "quick breads",\
        "palabras_clave": []\
    \},\
    "IMG_6192.jpeg": \{\
        "archivo": "IMG_6192.jpeg",\
        "titulo": "Bisquits",\
        "categoria": "quick breads",\
        "palabras_clave": []\
    \},\
    "IMG_6193.jpeg": \{\
        "archivo": "IMG_6193.jpeg",\
        "titulo": "Biscuits (2)",\
        "categoria": "quick breads",\
        "palabras_clave": []\
    \},\
    "IMG_6194.jpeg": \{\
        "archivo": "IMG_6194.jpeg",\
        "titulo": "IMG 6194",\
        "categoria": "",\
        "palabras_clave": []\
    \},\
    "IMG_6195.jpeg": \{\
        "archivo": "IMG_6195.jpeg",\
        "titulo": "IGalletas  mam\'e1 Olguita",\
        "categoria": "quick breads",\
        "palabras_clave": []\
    \},\
    "IMG_6196.jpeg": \{\
        "archivo": "IMG_6196.jpeg",\
        "titulo": "Galletas Mam\'e1 Olguita",\
        "categoria": "quick breads",\
        "palabras_clave": []\
    \}\
\}}